odoo/addons/project_tag_security/README.rst
odoo/addons/project_tag_security/__init__.py
odoo/addons/project_tag_security/__manifest__.py
odoo/addons/project_tag_security/i18n/es.po
odoo/addons/project_tag_security/i18n/it.po
odoo/addons/project_tag_security/i18n/project_tag_security.pot
odoo/addons/project_tag_security/i18n/pt_BR.po
odoo/addons/project_tag_security/i18n/sv.po
odoo/addons/project_tag_security/models/__init__.py
odoo/addons/project_tag_security/models/project_project.py
odoo/addons/project_tag_security/models/project_tags.py
odoo/addons/project_tag_security/models/project_task.py
odoo/addons/project_tag_security/readme/CONTRIBUTORS.md
odoo/addons/project_tag_security/readme/DESCRIPTION.md
odoo/addons/project_tag_security/readme/USAGE.md
odoo/addons/project_tag_security/static/description/icon.png
odoo/addons/project_tag_security/static/description/index.html
odoo/addons/project_tag_security/tests/__init__.py
odoo/addons/project_tag_security/tests/test_project_tag_security.py
odoo/addons/project_tag_security/views/project_tags_views.xml
odoo_addon_project_tag_security-18.0.1.0.1.dist-info/METADATA
odoo_addon_project_tag_security-18.0.1.0.1.dist-info/WHEEL
odoo_addon_project_tag_security-18.0.1.0.1.dist-info/top_level.txt
odoo_addon_project_tag_security-18.0.1.0.1.dist-info/RECORD
